escape/__init__.py
escape/errors.py
escape/proxy_module.py
escape/py.typed
escape/wrapper.py
exception_escaping-0.0.9.dist-info/LICENSE
exception_escaping-0.0.9.dist-info/METADATA
exception_escaping-0.0.9.dist-info/WHEEL
exception_escaping-0.0.9.dist-info/top_level.txt
exception_escaping-0.0.9.dist-info/RECORD
